README.md
setup.py
krepresentatives/ClusteringAlgorithm.py
krepresentatives/__init__.py
krepresentatives/kRepresentatives.py
krepresentatives.egg-info/PKG-INFO
krepresentatives.egg-info/SOURCES.txt
krepresentatives.egg-info/dependency_links.txt
krepresentatives.egg-info/top_level.txt