Metadata-Version: 2.1
Name: krepresentatives
Version: 1.1.2
Summary: A package for k-Representatives and LSH-k-Representatives
Home-page: https://github.com/
Author: Toan Nguyen Mau and Van-Nam Huynh
Author-email: nmtoan91@jaist.ac.jp
License: UNKNOWN
Platform: UNKNOWN
Classifier: Programming Language :: Python :: 3
Classifier: License :: OSI Approved :: MIT License
Classifier: Operating System :: OS Independent
Requires-Python: >=3.6
